spi_adapter/__init__.py
spi_adapter/py.typed
spi_adapter-0.0.6.dist-info/METADATA
spi_adapter-0.0.6.dist-info/WHEEL
spi_adapter-0.0.6.dist-info/licenses/LICENSE
spi_adapter-0.0.6.dist-info/RECORD
