Metadata-Version: 2.1
Name: spi_adapter
Version: 0.0.6
Summary: A simple USB to SPI adapter that works.
Project-URL: Homepage, https://github.com/zapta/spi_adapter
Project-URL: Documentation, https://spi-adapter.readthedocs.io/en/latest
Project-URL: Repository, https://github.com/zapta/spi_adapter.git
Project-URL: Bug Tracker, https://github.com/zapta/spi_adapter/issues
Author-email: Zapta <zapta@zapta.com>
License-File: LICENSE
Classifier: Development Status :: 5 - Production/Stable
Classifier: License :: CC0 1.0 Universal (CC0 1.0) Public Domain Dedication
Classifier: Operating System :: OS Independent
Classifier: Programming Language :: Python :: 3
Requires-Python: >=3.7
Requires-Dist: pyserial>=3.5
